sqldiffer/__init__.py
sqldiffer/cli.py
sqldiffer/db/__init__.py
sqldiffer/db/connection.py
sqldiffer/db/credential.py
sqldiffer/db/sql.py
sqldiffer/differ.py
sqldiffer/exceptions.py
sqldiffer/logger.py
sqldiffer/main.py
sqldiffer-0.1.2.dist-info/entry_points.txt
sqldiffer-0.1.2.dist-info/LICENSE
sqldiffer-0.1.2.dist-info/WHEEL
sqldiffer-0.1.2.dist-info/METADATA
sqldiffer-0.1.2.dist-info/RECORD
