Metadata-Version: 2.1
Name: sqldiffer
Version: 0.1.2
Summary: Check the difference of MySQL schema (CREATE TABLE)
Home-page: https://github.com/homoluctus/sqldiffer
License: MIT
Keywords: MySQL,Database,Schema
Author: homoluctus
Author-email: w.slife18sy@gmail.com
Requires-Python: >=3.8,<4.0
Classifier: License :: OSI Approved :: MIT License
Classifier: Programming Language :: Python :: 3
Classifier: Programming Language :: Python :: 3.8
Requires-Dist: pymysql (>=0.10.0,<0.11.0)
Project-URL: Repository, https://github.com/homoluctus/sqldiffer
